odoo8_addon_website_sale_recently_viewed_products-8.0.1.0.0.99.dev36-py2.7-nspkg.pth
odoo8_addon_website_sale_recently_viewed_products-8.0.1.0.0.99.dev36.dist-info/METADATA
odoo8_addon_website_sale_recently_viewed_products-8.0.1.0.0.99.dev36.dist-info/RECORD
odoo8_addon_website_sale_recently_viewed_products-8.0.1.0.0.99.dev36.dist-info/WHEEL
odoo8_addon_website_sale_recently_viewed_products-8.0.1.0.0.99.dev36.dist-info/namespace_packages.txt
odoo8_addon_website_sale_recently_viewed_products-8.0.1.0.0.99.dev36.dist-info/top_level.txt
odoo_addons/website_sale_recently_viewed_products/README.rst
odoo_addons/website_sale_recently_viewed_products/__init__.py
odoo_addons/website_sale_recently_viewed_products/__openerp__.py
odoo_addons/website_sale_recently_viewed_products/controllers/__init__.py
odoo_addons/website_sale_recently_viewed_products/controllers/main.py
odoo_addons/website_sale_recently_viewed_products/i18n/am.po
odoo_addons/website_sale_recently_viewed_products/i18n/ar.po
odoo_addons/website_sale_recently_viewed_products/i18n/bg.po
odoo_addons/website_sale_recently_viewed_products/i18n/bs.po
odoo_addons/website_sale_recently_viewed_products/i18n/ca.po
odoo_addons/website_sale_recently_viewed_products/i18n/ca_ES.po
odoo_addons/website_sale_recently_viewed_products/i18n/cs.po
odoo_addons/website_sale_recently_viewed_products/i18n/da.po
odoo_addons/website_sale_recently_viewed_products/i18n/de.po
odoo_addons/website_sale_recently_viewed_products/i18n/el_GR.po
odoo_addons/website_sale_recently_viewed_products/i18n/en_GB.po
odoo_addons/website_sale_recently_viewed_products/i18n/es.po
odoo_addons/website_sale_recently_viewed_products/i18n/es_AR.po
odoo_addons/website_sale_recently_viewed_products/i18n/es_CL.po
odoo_addons/website_sale_recently_viewed_products/i18n/es_CO.po
odoo_addons/website_sale_recently_viewed_products/i18n/es_CR.po
odoo_addons/website_sale_recently_viewed_products/i18n/es_DO.po
odoo_addons/website_sale_recently_viewed_products/i18n/es_EC.po
odoo_addons/website_sale_recently_viewed_products/i18n/es_ES.po
odoo_addons/website_sale_recently_viewed_products/i18n/es_MX.po
odoo_addons/website_sale_recently_viewed_products/i18n/es_PE.po
odoo_addons/website_sale_recently_viewed_products/i18n/es_PY.po
odoo_addons/website_sale_recently_viewed_products/i18n/es_VE.po
odoo_addons/website_sale_recently_viewed_products/i18n/et.po
